{
    "name": "ShippingOrder",
    "fields": [],
    "relationships": [
        {
            "relationshipType": "one-to-one",
            "otherEntityName": "batchShipmentRateDetail",
            "otherEntityRelationshipName": "shippingOrder",
            "relationshipName": "batchShipmentRateDetail",
            "otherEntityField": "id",
            "ownerSide": true
        }
    ],
    "changelogDate": "20191220102001",
    "entityTableName": "shipping_order",
    "dto": "no",
    "pagination": "no",
    "service": "no",
    "jpaMetamodelFiltering": false,
    "fluentMethods": true,
    "readOnly": false,
    "clientRootFolder": "",
    "applications": "*"
}